evers2010/__init__.py
evers2010/constants.py
evers2010/photo_params.py
evers2010/photosynthesis.py
evers2010/stomata.py
evers2010/version.py
evers2010/weather.py
evers2010-0.1.1.dist-info/AUTHORS.rst
evers2010-0.1.1.dist-info/LICENSE
evers2010-0.1.1.dist-info/METADATA
evers2010-0.1.1.dist-info/WHEEL
evers2010-0.1.1.dist-info/top_level.txt
evers2010-0.1.1.dist-info/RECORD
